L3rotect/AntiAnalysis.py
L3rotect/__init__.py
pyL33_rotect-0.1.dist-info/METADATA
pyL33_rotect-0.1.dist-info/WHEEL
pyL33_rotect-0.1.dist-info/top_level.txt
pyL33_rotect-0.1.dist-info/RECORD
